<root>
  <Gear id="1">
    <materials>
      <material>
        <id>1</id>
        <material_name>Bar</material_name>
      </material>
      <material>
        <id>2</id>
        <material_name>Leather</material_name>
      </material>
    </materials>
    <category>
      <id>1</id>
      <name>Warrior Weapons</name>
    </category>
    <equipment>
      <id>1</id>
      <equipment_name>Claymore</equipment_name>
      <category>1</category>
    </equipment>
    <recipes>
      <recipe>
        <equipment_id>1</equipment_id>
        <material_id>1</material_id>
        <material_quantity>20</material_quantity>
      </recipe>
      <recipe>
        <equipment_id>1</equipment_id>
        <material_id>2</material_id>
        <material_quantity>12</material_quantity>
      </recipe>
    </recipes>
  </Gear>
  <Gear id="2">
    <materials>
      <material>
        <id>3</id>
        <material_name>Plank</material_name>
      </material>
    </materials>
    <category>
      <id>2</id>
      <name>Hunter Weapons</name>
    </category>
    <equipment>
      <id>2</id>
      <equipment_name>Bow</equipment_name>
      <category>2</category>
    </equipment>
    <recipes>
      <recipe>
        <equipment_id>2</equipment_id>
        <material_id>3</material_id>
        <material_quantity>32</material_quantity>
      </recipe>
    </recipes>
  </Gear>
  <Gear id="3">
    <materials>
      <material>
        <id>3</id>
        <material_name>Plank</material_name>
      </material>
      <material>
        <id>1</id>
        <material_name>Bar</material_name>
      </material>
    </materials>
    <category>
      <id>3</id>
      <name>Mage Weapons</name>
    </category>
    <equipment>
      <id>3</id>
      <equipment_name>Fire Staff</equipment_name>
      <category>3</category>
    </equipment>
    <recipes>
      <recipe>
        <equipment_id>3</equipment_id>
        <material_id>3</material_id>
        <material_quantity>16</material_quantity>
      </recipe>
      <recipe>
        <equipment_id>3</equipment_id>
        <material_id>1</material_id>
        <material_quantity>8</material_quantity>
      </recipe>
    </recipes>
  </Gear>
  <Gear id="4">
    <materials>
      <material>
        <id>1</id>
        <material_name>Bar</material_name>
      </material>
    </materials>
    <category>
      <id>4</id>
      <name>Warrior Armours</name>
    </category>
    <equipment>
      <id>4</id>
      <equipment_name>Knight Armor</equipment_name>
      <category>4</category>
    </equipment>
    <recipes>
      <recipe>
        <equipment_id>4</equipment_id>
        <material_id>1</material_id>
        <material_quantity>16</material_quantity>
      </recipe>
    </recipes>
  </Gear>
  <Gear id="5">
    <materials>
      <material>
        <id>1</id>
        <material_name>Bar</material_name>
      </material>
      <material>
        <id>5</id>
        <material_name>Artifact</material_name>
      </material>
    </materials>
    <category>
      <id>4</id>
      <name>Warrior Armours</name>
    </category>
    <equipment>
      <id>5</id>
      <equipment_name>Judicator Armor</equipment_name>
      <category>4</category>
    </equipment>
    <recipes>
      <recipe>
        <equipment_id>5</equipment_id>
        <material_id>1</material_id>
        <material_quantity>16</material_quantity>
      </recipe>
      <recipe>
        <equipment_id>5</equipment_id>
        <material_id>5</material_id>
        <material_quantity>1</material_quantity>
      </recipe>
    </recipes>
  </Gear>
  <Gear id="6">
    <materials>
      <material>
        <id>1</id>
        <material_name>Bar</material_name>
      </material>
    </materials>
    <category>
      <id>4</id>
      <name>Warrior Armours</name>
    </category>
    <equipment>
      <id>6</id>
      <equipment_name>Soldier Boots</equipment_name>
      <category>4</category>
    </equipment>
    <recipes>
      <recipe>
        <equipment_id>6</equipment_id>
        <material_id>1</material_id>
        <material_quantity>8</material_quantity>
      </recipe>
    </recipes>
  </Gear>
  <Gear id="7">
    <materials>
      <material>
        <id>1</id>
        <material_name>Bar</material_name>
      </material>
    </materials>
    <category>
      <id>4</id>
      <name>Warrior Armours</name>
    </category>
    <equipment>
      <id>7</id>
      <equipment_name>Knight Boots</equipment_name>
      <category>4</category>
    </equipment>
    <recipes>
      <recipe>
        <equipment_id>7</equipment_id>
        <material_id>1</material_id>
        <material_quantity>8</material_quantity>
      </recipe>
    </recipes>
  </Gear>
  <Gear id="8">
    <materials>
      <material>
        <id>1</id>
        <material_name>Bar</material_name>
      </material>
    </materials>
    <category>
      <id>4</id>
      <name>Warrior Armours</name>
    </category>
    <equipment>
      <id>8</id>
      <equipment_name>Guardian Boots</equipment_name>
      <category>4</category>
    </equipment>
    <recipes>
      <recipe>
        <equipment_id>8</equipment_id>
        <material_id>1</material_id>
        <material_quantity>8</material_quantity>
      </recipe>
    </recipes>
  </Gear>
  <Gear id="9">
    <materials>
      <material>
        <id>1</id>
        <material_name>Bar</material_name>
      </material>
      <material>
        <id>5</id>
        <material_name>Artifact</material_name>
      </material>
    </materials>
    <category>
      <id>4</id>
      <name>Warrior Armours</name>
    </category>
    <equipment>
      <id>9</id>
      <equipment_name>Graveguard Boots</equipment_name>
      <category>4</category>
    </equipment>
    <recipes>
      <recipe>
        <equipment_id>9</equipment_id>
        <material_id>1</material_id>
        <material_quantity>8</material_quantity>
      </recipe>
      <recipe>
        <equipment_id>9</equipment_id>
        <material_id>5</material_id>
        <material_quantity>1</material_quantity>
      </recipe>
    </recipes>
  </Gear>
  <Gear id="10">
    <materials>
      <material>
        <id>1</id>
        <material_name>Bar</material_name>
      </material>
    </materials>
    <category>
      <id>4</id>
      <name>Warrior Armours</name>
    </category>
    <equipment>
      <id>10</id>
      <equipment_name>Demon Boots</equipment_name>
      <category>4</category>
    </equipment>
    <recipes>
      <recipe>
        <equipment_id>10</equipment_id>
        <material_id>1</material_id>
        <material_quantity>8</material_quantity>
      </recipe>
    </recipes>
  </Gear>
  <Gear id="11">
    <materials>
      <material>
        <id>1</id>
        <material_name>Bar</material_name>
      </material>
      <material>
        <id>5</id>
        <material_name>Artifact</material_name>
      </material>
    </materials>
    <category>
      <id>4</id>
      <name>Warrior Armours</name>
    </category>
    <equipment>
      <id>11</id>
      <equipment_name>Judicator Boots</equipment_name>
      <category>4</category>
    </equipment>
    <recipes>
      <recipe>
        <equipment_id>11</equipment_id>
        <material_id>1</material_id>
        <material_quantity>8</material_quantity>
      </recipe>
      <recipe>
        <equipment_id>11</equipment_id>
        <material_id>5</material_id>
        <material_quantity>1</material_quantity>
      </recipe>
    </recipes>
  </Gear>
  <Gear id="12">
    <materials>
      <material>
        <id>1</id>
        <material_name>Bar</material_name>
      </material>
      <material>
        <id>5</id>
        <material_name>Artifact</material_name>
      </material>
    </materials>
    <category>
      <id>4</id>
      <name>Warrior Armours</name>
    </category>
    <equipment>
      <id>12</id>
      <equipment_name>Boots of Valor</equipment_name>
      <category>4</category>
    </equipment>
    <recipes>
      <recipe>
        <equipment_id>12</equipment_id>
        <material_id>1</material_id>
        <material_quantity>8</material_quantity>
      </recipe>
      <recipe>
        <equipment_id>12</equipment_id>
        <material_id>5</material_id>
        <material_quantity>1</material_quantity>
      </recipe>
    </recipes>
  </Gear>
  <Gear id="15">
    <materials>
      <material>
        <id>1</id>
        <material_name>Bar</material_name>
      </material>
    </materials>
    <category>
      <id>4</id>
      <name>Warrior Armours</name>
    </category>
    <equipment>
      <id>15</id>
      <equipment_name>Soldier Armor</equipment_name>
      <category>4</category>
    </equipment>
    <recipes>
      <recipe>
        <equipment_id>15</equipment_id>
        <material_id>1</material_id>
        <material_quantity>16</material_quantity>
      </recipe>
    </recipes>
  </Gear>
  <Gear id="16">
    <materials>
      <material>
        <id>1</id>
        <material_name>Bar</material_name>
      </material>
    </materials>
    <category>
      <id>4</id>
      <name>Warrior Armours</name>
    </category>
    <equipment>
      <id>16</id>
      <equipment_name>Guardian Armor</equipment_name>
      <category>4</category>
    </equipment>
    <recipes>
      <recipe>
        <equipment_id>16</equipment_id>
        <material_id>1</material_id>
        <material_quantity>16</material_quantity>
      </recipe>
    </recipes>
  </Gear>
  <Gear id="17">
    <materials>
      <material>
        <id>1</id>
        <material_name>Bar</material_name>
      </material>
      <material>
        <id>5</id>
        <material_name>Artifact</material_name>
      </material>
    </materials>
    <category>
      <id>4</id>
      <name>Warrior Armours</name>
    </category>
    <equipment>
      <id>17</id>
      <equipment_name>Graveguard Armor</equipment_name>
      <category>4</category>
    </equipment>
    <recipes>
      <recipe>
        <equipment_id>17</equipment_id>
        <material_id>1</material_id>
        <material_quantity>16</material_quantity>
      </recipe>
      <recipe>
        <equipment_id>17</equipment_id>
        <material_id>5</material_id>
        <material_quantity>1</material_quantity>
      </recipe>
    </recipes>
  </Gear>
  <Gear id="18">
    <materials>
      <material>
        <id>1</id>
        <material_name>Bar</material_name>
      </material>
      <material>
        <id>5</id>
        <material_name>Artifact</material_name>
      </material>
    </materials>
    <category>
      <id>4</id>
      <name>Warrior Armours</name>
    </category>
    <equipment>
      <id>18</id>
      <equipment_name>Demon Armor</equipment_name>
      <category>4</category>
    </equipment>
    <recipes>
      <recipe>
        <equipment_id>18</equipment_id>
        <material_id>1</material_id>
        <material_quantity>16</material_quantity>
      </recipe>
      <recipe>
        <equipment_id>18</equipment_id>
        <material_id>5</material_id>
        <material_quantity>1</material_quantity>
      </recipe>
    </recipes>
  </Gear>
  <Gear id="19">
    <materials>
      <material>
        <id>1</id>
        <material_name>Bar</material_name>
      </material>
      <material>
        <id>5</id>
        <material_name>Artifact</material_name>
      </material>
    </materials>
    <category>
      <id>4</id>
      <name>Warrior Armours</name>
    </category>
    <equipment>
      <id>19</id>
      <equipment_name>Judicator Armor</equipment_name>
      <category>4</category>
    </equipment>
    <recipes>
      <recipe>
        <equipment_id>19</equipment_id>
        <material_id>1</material_id>
        <material_quantity>16</material_quantity>
      </recipe>
      <recipe>
        <equipment_id>19</equipment_id>
        <material_id>5</material_id>
        <material_quantity>1</material_quantity>
      </recipe>
    </recipes>
  </Gear>
  <Gear id="20">
    <materials>
      <material>
        <id>1</id>
        <material_name>Bar</material_name>
      </material>
      <material>
        <id>5</id>
        <material_name>Artifact</material_name>
      </material>
    </materials>
    <category>
      <id>4</id>
      <name>Warrior Armours</name>
    </category>
    <equipment>
      <id>20</id>
      <equipment_name>Armor of Valor</equipment_name>
      <category>4</category>
    </equipment>
    <recipes>
      <recipe>
        <equipment_id>20</equipment_id>
        <material_id>1</material_id>
        <material_quantity>16</material_quantity>
      </recipe>
      <recipe>
        <equipment_id>20</equipment_id>
        <material_id>5</material_id>
        <material_quantity>1</material_quantity>
      </recipe>
    </recipes>
  </Gear>
  <Gear id="22">
    <materials>
      <material>
        <id>1</id>
        <material_name>Bar</material_name>
      </material>
    </materials>
    <category>
      <id>4</id>
      <name>Warrior Armours</name>
    </category>
    <equipment>
      <id>22</id>
      <equipment_name>Soldier Helmet</equipment_name>
      <category>4</category>
    </equipment>
    <recipes>
      <recipe>
        <equipment_id>22</equipment_id>
        <material_id>1</material_id>
        <material_quantity>8</material_quantity>
      </recipe>
    </recipes>
  </Gear>
  <Gear id="23">
    <materials>
      <material>
        <id>1</id>
        <material_name>Bar</material_name>
      </material>
    </materials>
    <category>
      <id>4</id>
      <name>Warrior Armours</name>
    </category>
    <equipment>
      <id>23</id>
      <equipment_name>Knight Helmet</equipment_name>
      <category>4</category>
    </equipment>
    <recipes>
      <recipe>
        <equipment_id>23</equipment_id>
        <material_id>1</material_id>
        <material_quantity>8</material_quantity>
      </recipe>
    </recipes>
  </Gear>
  <Gear id="24">
    <materials>
      <material>
        <id>1</id>
        <material_name>Bar</material_name>
      </material>
    </materials>
    <category>
      <id>4</id>
      <name>Warrior Armours</name>
    </category>
    <equipment>
      <id>24</id>
      <equipment_name>Guardian Helmet</equipment_name>
      <category>4</category>
    </equipment>
    <recipes>
      <recipe>
        <equipment_id>24</equipment_id>
        <material_id>1</material_id>
        <material_quantity>8</material_quantity>
      </recipe>
    </recipes>
  </Gear>
  <Gear id="25">
    <materials>
      <material>
        <id>1</id>
        <material_name>Bar</material_name>
      </material>
      <material>
        <id>5</id>
        <material_name>Artifact</material_name>
      </material>
    </materials>
    <category>
      <id>4</id>
      <name>Warrior Armours</name>
    </category>
    <equipment>
      <id>25</id>
      <equipment_name>Graveguard Helmet</equipment_name>
      <category>4</category>
    </equipment>
    <recipes>
      <recipe>
        <equipment_id>25</equipment_id>
        <material_id>1</material_id>
        <material_quantity>8</material_quantity>
      </recipe>
      <recipe>
        <equipment_id>25</equipment_id>
        <material_id>5</material_id>
        <material_quantity>1</material_quantity>
      </recipe>
    </recipes>
  </Gear>
  <Gear id="26">
    <materials>
      <material>
        <id>1</id>
        <material_name>Bar</material_name>
      </material>
      <material>
        <id>5</id>
        <material_name>Artifact</material_name>
      </material>
    </materials>
    <category>
      <id>4</id>
      <name>Warrior Armours</name>
    </category>
    <equipment>
      <id>26</id>
      <equipment_name>Demon Helmet</equipment_name>
      <category>4</category>
    </equipment>
    <recipes>
      <recipe>
        <equipment_id>26</equipment_id>
        <material_id>1</material_id>
        <material_quantity>8</material_quantity>
      </recipe>
      <recipe>
        <equipment_id>26</equipment_id>
        <material_id>5</material_id>
        <material_quantity>1</material_quantity>
      </recipe>
    </recipes>
  </Gear>
  <Gear id="27">
    <materials>
      <material>
        <id>1</id>
        <material_name>Bar</material_name>
      </material>
      <material>
        <id>5</id>
        <material_name>Artifact</material_name>
      </material>
    </materials>
    <category>
      <id>4</id>
      <name>Warrior Armours</name>
    </category>
    <equipment>
      <id>27</id>
      <equipment_name>Judicator Helmet</equipment_name>
      <category>4</category>
    </equipment>
    <recipes>
      <recipe>
        <equipment_id>27</equipment_id>
        <material_id>1</material_id>
        <material_quantity>8</material_quantity>
      </recipe>
      <recipe>
        <equipment_id>27</equipment_id>
        <material_id>5</material_id>
        <material_quantity>1</material_quantity>
      </recipe>
    </recipes>
  </Gear>
  <Gear id="28">
    <materials>
      <material>
        <id>1</id>
        <material_name>Bar</material_name>
      </material>
      <material>
        <id>5</id>
        <material_name>Artifact</material_name>
      </material>
    </materials>
    <category>
      <id>4</id>
      <name>Warrior Armours</name>
    </category>
    <equipment>
      <id>28</id>
      <equipment_name>Helmet of Valor</equipment_name>
      <category>4</category>
    </equipment>
    <recipes>
      <recipe>
        <equipment_id>28</equipment_id>
        <material_id>1</material_id>
        <material_quantity>8</material_quantity>
      </recipe>
      <recipe>
        <equipment_id>28</equipment_id>
        <material_id>5</material_id>
        <material_quantity>1</material_quantity>
      </recipe>
    </recipes>
  </Gear>
  <Gear id="29">
    <materials>
      <material>
        <id>1</id>
        <material_name>Bar</material_name>
      </material>
      <material>
        <id>2</id>
        <material_name>Leather</material_name>
      </material>
      <material>
        <id>5</id>
        <material_name>Artifact</material_name>
      </material>
    </materials>
    <category>
      <id>1</id>
      <name>Warrior Weapons</name>
    </category>
    <equipment>
      <id>29</id>
      <equipment_name>Kingmaker</equipment_name>
      <category>1</category>
    </equipment>
    <recipes>
      <recipe>
        <equipment_id>29</equipment_id>
        <material_id>1</material_id>
        <material_quantity>20</material_quantity>
      </recipe>
      <recipe>
        <equipment_id>29</equipment_id>
        <material_id>2</material_id>
        <material_quantity>12</material_quantity>
      </recipe>
      <recipe>
        <equipment_id>29</equipment_id>
        <material_id>5</material_id>
        <material_quantity>1</material_quantity>
      </recipe>
    </recipes>
  </Gear>
  <Gear id="30">
    <materials>
      <material>
        <id>1</id>
        <material_name>Bar</material_name>
      </material>
      <material>
        <id>2</id>
        <material_name>Leather</material_name>
      </material>
    </materials>
    <category>
      <id>1</id>
      <name>Warrior Weapons</name>
    </category>
    <equipment>
      <id>30</id>
      <equipment_name>Dual Sword</equipment_name>
      <category>1</category>
    </equipment>
    <recipes>
      <recipe>
        <equipment_id>30</equipment_id>
        <material_id>1</material_id>
        <material_quantity>20</material_quantity>
      </recipe>
      <recipe>
        <equipment_id>30</equipment_id>
        <material_id>2</material_id>
        <material_quantity>12</material_quantity>
      </recipe>
    </recipes>
  </Gear>
  <Gear id="31">
    <materials>
      <material>
        <id>1</id>
        <material_name>Bar</material_name>
      </material>
      <material>
        <id>2</id>
        <material_name>Leather</material_name>
      </material>
      <material>
        <id>5</id>
        <material_name>Artifact</material_name>
      </material>
    </materials>
    <category>
      <id>1</id>
      <name>Warrior Weapons</name>
    </category>
    <equipment>
      <id>31</id>
      <equipment_name>Clarent Blade</equipment_name>
      <category>1</category>
    </equipment>
    <recipes>
      <recipe>
        <equipment_id>31</equipment_id>
        <material_id>1</material_id>
        <material_quantity>16</material_quantity>
      </recipe>
      <recipe>
        <equipment_id>31</equipment_id>
        <material_id>2</material_id>
        <material_quantity>8</material_quantity>
      </recipe>
      <recipe>
        <equipment_id>31</equipment_id>
        <material_id>5</material_id>
        <material_quantity>1</material_quantity>
      </recipe>
    </recipes>
  </Gear>
  <Gear id="32">
    <materials>
      <material>
        <id>1</id>
        <material_name>Bar</material_name>
      </material>
      <material>
        <id>2</id>
        <material_name>Leather</material_name>
      </material>
      <material>
        <id>5</id>
        <material_name>Artifact</material_name>
      </material>
    </materials>
    <category>
      <id>1</id>
      <name>Warrior Weapons</name>
    </category>
    <equipment>
      <id>32</id>
      <equipment_name>Carving Sword</equipment_name>
      <category>1</category>
    </equipment>
    <recipes>
      <recipe>
        <equipment_id>32</equipment_id>
        <material_id>1</material_id>
        <material_quantity>20</material_quantity>
      </recipe>
      <recipe>
        <equipment_id>32</equipment_id>
        <material_id>2</material_id>
        <material_quantity>12</material_quantity>
      </recipe>
      <recipe>
        <equipment_id>32</equipment_id>
        <material_id>5</material_id>
        <material_quantity>1</material_quantity>
      </recipe>
    </recipes>
  </Gear>
  <Gear id="33">
    <materials>
      <material>
        <id>1</id>
        <material_name>Bar</material_name>
      </material>
      <material>
        <id>2</id>
        <material_name>Leather</material_name>
      </material>
      <material>
        <id>5</id>
        <material_name>Artifact</material_name>
      </material>
    </materials>
    <category>
      <id>1</id>
      <name>Warrior Weapons</name>
    </category>
    <equipment>
      <id>33</id>
      <equipment_name>Galatine Pair</equipment_name>
      <category>1</category>
    </equipment>
    <recipes>
      <recipe>
        <equipment_id>33</equipment_id>
        <material_id>1</material_id>
        <material_quantity>20</material_quantity>
      </recipe>
      <recipe>
        <equipment_id>33</equipment_id>
        <material_id>2</material_id>
        <material_quantity>12</material_quantity>
      </recipe>
      <recipe>
        <equipment_id>33</equipment_id>
        <material_id>5</material_id>
        <material_quantity>1</material_quantity>
      </recipe>
    </recipes>
  </Gear>
  <Gear id="34">
    <materials>
      <material>
        <id>1</id>
        <material_name>Bar</material_name>
      </material>
      <material>
        <id>3</id>
        <material_name>Plank</material_name>
      </material>
    </materials>
    <category>
      <id>1</id>
      <name>Warrior Weapons</name>
    </category>
    <equipment>
      <id>34</id>
      <equipment_name>Battle Axe</equipment_name>
      <category>1</category>
    </equipment>
    <recipes>
      <recipe>
        <equipment_id>34</equipment_id>
        <material_id>1</material_id>
        <material_quantity>16</material_quantity>
      </recipe>
      <recipe>
        <equipment_id>34</equipment_id>
        <material_id>3</material_id>
        <material_quantity>8</material_quantity>
      </recipe>
    </recipes>
  </Gear>
  <Gear id="35">
    <materials>
      <material>
        <id>1</id>
        <material_name>Bar</material_name>
      </material>
      <material>
        <id>3</id>
        <material_name>Plank</material_name>
      </material>
    </materials>
    <category>
      <id>1</id>
      <name>Warrior Weapons</name>
    </category>
    <equipment>
      <id>35</id>
      <equipment_name>Greataxe</equipment_name>
      <category>1</category>
    </equipment>
    <recipes>
      <recipe>
        <equipment_id>35</equipment_id>
        <material_id>1</material_id>
        <material_quantity>20</material_quantity>
      </recipe>
      <recipe>
        <equipment_id>35</equipment_id>
        <material_id>3</material_id>
        <material_quantity>12</material_quantity>
      </recipe>
    </recipes>
  </Gear>
  <Gear id="36">
    <materials>
      <material>
        <id>1</id>
        <material_name>Bar</material_name>
      </material>
      <material>
        <id>3</id>
        <material_name>Plank</material_name>
      </material>
      <material>
        <id>5</id>
        <material_name>Artifact</material_name>
      </material>
    </materials>
    <category>
      <id>1</id>
      <name>Warrior Weapons</name>
    </category>
    <equipment>
      <id>36</id>
      <equipment_name>Realmbreaker</equipment_name>
      <category>1</category>
    </equipment>
    <recipes>
      <recipe>
        <equipment_id>36</equipment_id>
        <material_id>1</material_id>
        <material_quantity>20</material_quantity>
      </recipe>
      <recipe>
        <equipment_id>36</equipment_id>
        <material_id>3</material_id>
        <material_quantity>12</material_quantity>
      </recipe>
      <recipe>
        <equipment_id>36</equipment_id>
        <material_id>5</material_id>
        <material_quantity>1</material_quantity>
      </recipe>
    </recipes>
  </Gear>
  <Gear id="37">
    <materials>
      <material>
        <id>1</id>
        <material_name>Bar</material_name>
      </material>
      <material>
        <id>3</id>
        <material_name>Plank</material_name>
      </material>
      <material>
        <id>5</id>
        <material_name>Artifact</material_name>
      </material>
    </materials>
    <category>
      <id>1</id>
      <name>Warrior Weapons</name>
    </category>
    <equipment>
      <id>37</id>
      <equipment_name>Carrioncaller</equipment_name>
      <category>1</category>
    </equipment>
    <recipes>
      <recipe>
        <equipment_id>37</equipment_id>
        <material_id>1</material_id>
        <material_quantity>20</material_quantity>
      </recipe>
      <recipe>
        <equipment_id>37</equipment_id>
        <material_id>3</material_id>
        <material_quantity>12</material_quantity>
      </recipe>
      <recipe>
        <equipment_id>37</equipment_id>
        <material_id>5</material_id>
        <material_quantity>1</material_quantity>
      </recipe>
    </recipes>
  </Gear>
  <Gear id="38">
    <materials>
      <material>
        <id>1</id>
        <material_name>Bar</material_name>
      </material>
      <material>
        <id>3</id>
        <material_name>Plank</material_name>
      </material>
      <material>
        <id>5</id>
        <material_name>Artifact</material_name>
      </material>
    </materials>
    <category>
      <id>1</id>
      <name>Warrior Weapons</name>
    </category>
    <equipment>
      <id>38</id>
      <equipment_name>Infernal Scythe</equipment_name>
      <category>1</category>
    </equipment>
    <recipes>
      <recipe>
        <equipment_id>38</equipment_id>
        <material_id>1</material_id>
        <material_quantity>20</material_quantity>
      </recipe>
      <recipe>
        <equipment_id>38</equipment_id>
        <material_id>3</material_id>
        <material_quantity>12</material_quantity>
      </recipe>
      <recipe>
        <equipment_id>38</equipment_id>
        <material_id>5</material_id>
        <material_quantity>1</material_quantity>
      </recipe>
    </recipes>
  </Gear>
  <Gear id="39">
    <materials>
      <material>
        <id>1</id>
        <material_name>Bar</material_name>
      </material>
      <material>
        <id>3</id>
        <material_name>Plank</material_name>
      </material>
      <material>
        <id>5</id>
        <material_name>Artifact</material_name>
      </material>
    </materials>
    <category>
      <id>1</id>
      <name>Warrior Weapons</name>
    </category>
    <equipment>
      <id>39</id>
      <equipment_name>Bear Paws</equipment_name>
      <category>1</category>
    </equipment>
    <recipes>
      <recipe>
        <equipment_id>39</equipment_id>
        <material_id>1</material_id>
        <material_quantity>20</material_quantity>
      </recipe>
      <recipe>
        <equipment_id>39</equipment_id>
        <material_id>3</material_id>
        <material_quantity>12</material_quantity>
      </recipe>
      <recipe>
        <equipment_id>39</equipment_id>
        <material_id>5</material_id>
        <material_quantity>1</material_quantity>
      </recipe>
    </recipes>
  </Gear>
  <Gear id="40">
    <materials>
      <material>
        <id>1</id>
        <material_name>Bar</material_name>
      </material>
      <material>
        <id>4</id>
        <material_name>Cloth</material_name>
      </material>
    </materials>
    <category>
      <id>1</id>
      <name>Warrior Weapons</name>
    </category>
    <equipment>
      <id>40</id>
      <equipment_name>Mace</equipment_name>
      <category>1</category>
    </equipment>
    <recipes>
      <recipe>
        <equipment_id>40</equipment_id>
        <material_id>1</material_id>
        <material_quantity>16</material_quantity>
      </recipe>
      <recipe>
        <equipment_id>40</equipment_id>
        <material_id>4</material_id>
        <material_quantity>8</material_quantity>
      </recipe>
    </recipes>
  </Gear>
  <Gear id="41">
    <materials>
      <material>
        <id>1</id>
        <material_name>Bar</material_name>
      </material>
      <material>
        <id>4</id>
        <material_name>Cloth</material_name>
      </material>
      <material>
        <id>5</id>
        <material_name>Artifact</material_name>
      </material>
    </materials>
    <category>
      <id>1</id>
      <name>Warrior Weapons</name>
    </category>
    <equipment>
      <id>41</id>
      <equipment_name>Incubus Mace</equipment_name>
      <category>1</category>
    </equipment>
    <recipes>
      <recipe>
        <equipment_id>41</equipment_id>
        <material_id>1</material_id>
        <material_quantity>16</material_quantity>
      </recipe>
      <recipe>
        <equipment_id>41</equipment_id>
        <material_id>4</material_id>
        <material_quantity>8</material_quantity>
      </recipe>
      <recipe>
        <equipment_id>41</equipment_id>
        <material_id>5</material_id>
        <material_quantity>1</material_quantity>
      </recipe>
    </recipes>
  </Gear>
  <Gear id="42">
    <materials>
      <material>
        <id>1</id>
        <material_name>Bar</material_name>
      </material>
      <material>
        <id>4</id>
        <material_name>Cloth</material_name>
      </material>
    </materials>
    <category>
      <id>1</id>
      <name>Warrior Weapons</name>
    </category>
    <equipment>
      <id>42</id>
      <equipment_name>Heavy Mace</equipment_name>
      <category>1</category>
    </equipment>
    <recipes>
      <recipe>
        <equipment_id>42</equipment_id>
        <material_id>1</material_id>
        <material_quantity>20</material_quantity>
      </recipe>
      <recipe>
        <equipment_id>42</equipment_id>
        <material_id>4</material_id>
        <material_quantity>12</material_quantity>
      </recipe>
    </recipes>
  </Gear>
  <Gear id="43">
    <materials>
      <material>
        <id>1</id>
        <material_name>Bar</material_name>
      </material>
      <material>
        <id>4</id>
        <material_name>Cloth</material_name>
      </material>
      <material>
        <id>5</id>
        <material_name>Artifact</material_name>
      </material>
    </materials>
    <category>
      <id>1</id>
      <name>Warrior Weapons</name>
    </category>
    <equipment>
      <id>43</id>
      <equipment_name>Camlan Mace</equipment_name>
      <category>1</category>
    </equipment>
    <recipes>
      <recipe>
        <equipment_id>43</equipment_id>
        <material_id>1</material_id>
        <material_quantity>20</material_quantity>
      </recipe>
      <recipe>
        <equipment_id>43</equipment_id>
        <material_id>4</material_id>
        <material_quantity>12</material_quantity>
      </recipe>
      <recipe>
        <equipment_id>43</equipment_id>
        <material_id>5</material_id>
        <material_quantity>1</material_quantity>
      </recipe>
    </recipes>
  </Gear>
  <Gear id="44">
    <materials>
      <material>
        <id>1</id>
        <material_name>Bar</material_name>
      </material>
      <material>
        <id>4</id>
        <material_name>Cloth</material_name>
      </material>
    </materials>
    <category>
      <id>1</id>
      <name>Warrior Weapons</name>
    </category>
    <equipment>
      <id>44</id>
      <equipment_name>Morning Star</equipment_name>
      <category>1</category>
    </equipment>
    <recipes>
      <recipe>
        <equipment_id>44</equipment_id>
        <material_id>1</material_id>
        <material_quantity>20</material_quantity>
      </recipe>
      <recipe>
        <equipment_id>44</equipment_id>
        <material_id>4</material_id>
        <material_quantity>12</material_quantity>
      </recipe>
    </recipes>
  </Gear>
  <Gear id="45">
    <materials>
      <material>
        <id>1</id>
        <material_name>Bar</material_name>
      </material>
      <material>
        <id>4</id>
        <material_name>Cloth</material_name>
      </material>
      <material>
        <id>5</id>
        <material_name>Artifact</material_name>
      </material>
    </materials>
    <category>
      <id>1</id>
      <name>Warrior Weapons</name>
    </category>
    <equipment>
      <id>45</id>
      <equipment_name>Oathkeepers</equipment_name>
      <category>1</category>
    </equipment>
    <recipes>
      <recipe>
        <equipment_id>45</equipment_id>
        <material_id>1</material_id>
        <material_quantity>20</material_quantity>
      </recipe>
      <recipe>
        <equipment_id>45</equipment_id>
        <material_id>4</material_id>
        <material_quantity>12</material_quantity>
      </recipe>
      <recipe>
        <equipment_id>45</equipment_id>
        <material_id>5</material_id>
        <material_quantity>1</material_quantity>
      </recipe>
    </recipes>
  </Gear>
  <Gear id="46">
    <materials>
      <material>
        <id>1</id>
        <material_name>Bar</material_name>
      </material>
    </materials>
    <category>
      <id>1</id>
      <name>Warrior Weapons</name>
    </category>
    <equipment>
      <id>46</id>
      <equipment_name>Hammer</equipment_name>
      <category>1</category>
    </equipment>
    <recipes>
      <recipe>
        <equipment_id>46</equipment_id>
        <material_id>1</material_id>
        <material_quantity>24</material_quantity>
      </recipe>
    </recipes>
  </Gear>
  <Gear id="47">
    <materials>
      <material>
        <id>1</id>
        <material_name>Bar</material_name>
      </material>
      <material>
        <id>4</id>
        <material_name>Cloth</material_name>
      </material>
    </materials>
    <category>
      <id>1</id>
      <name>Warrior Weapons</name>
    </category>
    <equipment>
      <id>47</id>
      <equipment_name>Great Hammer</equipment_name>
      <category>1</category>
    </equipment>
    <recipes>
      <recipe>
        <equipment_id>47</equipment_id>
        <material_id>1</material_id>
        <material_quantity>20</material_quantity>
      </recipe>
      <recipe>
        <equipment_id>47</equipment_id>
        <material_id>4</material_id>
        <material_quantity>12</material_quantity>
      </recipe>
    </recipes>
  </Gear>
  <Gear id="48">
    <materials>
      <material>
        <id>1</id>
        <material_name>Bar</material_name>
      </material>
      <material>
        <id>4</id>
        <material_name>Cloth</material_name>
      </material>
      <material>
        <id>5</id>
        <material_name>Artifact</material_name>
      </material>
    </materials>
    <category>
      <id>1</id>
      <name>Warrior Weapons</name>
    </category>
    <equipment>
      <id>48</id>
      <equipment_name>Hand of Justice</equipment_name>
      <category>1</category>
    </equipment>
    <recipes>
      <recipe>
        <equipment_id>48</equipment_id>
        <material_id>1</material_id>
        <material_quantity>20</material_quantity>
      </recipe>
      <recipe>
        <equipment_id>48</equipment_id>
        <material_id>4</material_id>
        <material_quantity>12</material_quantity>
      </recipe>
      <recipe>
        <equipment_id>48</equipment_id>
        <material_id>5</material_id>
        <material_quantity>1</material_quantity>
      </recipe>
    </recipes>
  </Gear>
  <Gear id="49">
    <materials>
      <material>
        <id>1</id>
        <material_name>Bar</material_name>
      </material>
      <material>
        <id>4</id>
        <material_name>Cloth</material_name>
      </material>
      <material>
        <id>5</id>
        <material_name>Artifact</material_name>
      </material>
    </materials>
    <category>
      <id>1</id>
      <name>Warrior Weapons</name>
    </category>
    <equipment>
      <id>49</id>
      <equipment_name>Tombhammer</equipment_name>
      <category>1</category>
    </equipment>
    <recipes>
      <recipe>
        <equipment_id>49</equipment_id>
        <material_id>1</material_id>
        <material_quantity>20</material_quantity>
      </recipe>
      <recipe>
        <equipment_id>49</equipment_id>
        <material_id>4</material_id>
        <material_quantity>12</material_quantity>
      </recipe>
      <recipe>
        <equipment_id>49</equipment_id>
        <material_id>5</material_id>
        <material_quantity>1</material_quantity>
      </recipe>
    </recipes>
  </Gear>
  <Gear id="50">
    <materials>
      <material>
        <id>1</id>
        <material_name>Bar</material_name>
      </material>
      <material>
        <id>4</id>
        <material_name>Cloth</material_name>
      </material>
    </materials>
    <category>
      <id>1</id>
      <name>Warrior Weapons</name>
    </category>
    <equipment>
      <id>50</id>
      <equipment_name>Polehammer</equipment_name>
      <category>1</category>
    </equipment>
    <recipes>
      <recipe>
        <equipment_id>50</equipment_id>
        <material_id>1</material_id>
        <material_quantity>20</material_quantity>
      </recipe>
      <recipe>
        <equipment_id>50</equipment_id>
        <material_id>4</material_id>
        <material_quantity>12</material_quantity>
      </recipe>
    </recipes>
  </Gear>
  <Gear id="51">
    <materials>
      <material>
        <id>1</id>
        <material_name>Bar</material_name>
      </material>
      <material>
        <id>4</id>
        <material_name>Cloth</material_name>
      </material>
      <material>
        <id>5</id>
        <material_name>Artifact</material_name>
      </material>
    </materials>
    <category>
      <id>1</id>
      <name>Warrior Weapons</name>
    </category>
    <equipment>
      <id>51</id>
      <equipment_name>Forge Hammer</equipment_name>
      <category>1</category>
    </equipment>
    <recipes>
      <recipe>
        <equipment_id>51</equipment_id>
        <material_id>1</material_id>
        <material_quantity>20</material_quantity>
      </recipe>
      <recipe>
        <equipment_id>51</equipment_id>
        <material_id>4</material_id>
        <material_quantity>12</material_quantity>
      </recipe>
      <recipe>
        <equipment_id>51</equipment_id>
        <material_id>5</material_id>
        <material_quantity>1</material_quantity>
      </recipe>
    </recipes>
  </Gear>
  <Gear id="52">
    <materials>
      <material>
        <id>1</id>
        <material_name>Bar</material_name>
      </material>
      <material>
        <id>4</id>
        <material_name>Cloth</material_name>
      </material>
      <material>
        <id>5</id>
        <material_name>Artifact</material_name>
      </material>
    </materials>
    <category>
      <id>1</id>
      <name>Warrior Weapons</name>
    </category>
    <equipment>
      <id>52</id>
      <equipment_name>Grovekeeper</equipment_name>
      <category>1</category>
    </equipment>
    <recipes>
      <recipe>
        <equipment_id>52</equipment_id>
        <material_id>1</material_id>
        <material_quantity>20</material_quantity>
      </recipe>
      <recipe>
        <equipment_id>52</equipment_id>
        <material_id>4</material_id>
        <material_quantity>12</material_quantity>
      </recipe>
      <recipe>
        <equipment_id>52</equipment_id>
        <material_id>5</material_id>
        <material_quantity>1</material_quantity>
      </recipe>
    </recipes>
  </Gear>
  <Gear id="53">
    <materials>
      <material>
        <id>1</id>
        <material_name>Bar</material_name>
      </material>
      <material>
        <id>2</id>
        <material_name>Leather</material_name>
      </material>
      <material>
        <id>5</id>
        <material_name>Artifact</material_name>
      </material>
    </materials>
    <category>
      <id>1</id>
      <name>Warrior Weapons</name>
    </category>
    <equipment>
      <id>53</id>
      <equipment_name>Fist of Avalon</equipment_name>
      <category>1</category>
    </equipment>
    <recipes>
      <recipe>
        <equipment_id>53</equipment_id>
        <material_id>1</material_id>
        <material_quantity>12</material_quantity>
      </recipe>
      <recipe>
        <equipment_id>53</equipment_id>
        <material_id>2</material_id>
        <material_quantity>20</material_quantity>
      </recipe>
      <recipe>
        <equipment_id>53</equipment_id>
        <material_id>5</material_id>
        <material_quantity>1</material_quantity>
      </recipe>
    </recipes>
  </Gear>
  <Gear id="54">
    <materials>
      <material>
        <id>1</id>
        <material_name>Bar</material_name>
      </material>
      <material>
        <id>2</id>
        <material_name>Leather</material_name>
      </material>
      <material>
        <id>5</id>
        <material_name>Artifact</material_name>
      </material>
    </materials>
    <category>
      <id>1</id>
      <name>Warrior Weapons</name>
    </category>
    <equipment>
      <id>54</id>
      <equipment_name>Hellfire Hands</equipment_name>
      <category>1</category>
    </equipment>
    <recipes>
      <recipe>
        <equipment_id>54</equipment_id>
        <material_id>1</material_id>
        <material_quantity>12</material_quantity>
      </recipe>
      <recipe>
        <equipment_id>54</equipment_id>
        <material_id>2</material_id>
        <material_quantity>20</material_quantity>
      </recipe>
      <recipe>
        <equipment_id>54</equipment_id>
        <material_id>5</material_id>
        <material_quantity>1</material_quantity>
      </recipe>
    </recipes>
  </Gear>
  <Gear id="55">
    <materials>
      <material>
        <id>1</id>
        <material_name>Bar</material_name>
      </material>
      <material>
        <id>2</id>
        <material_name>Leather</material_name>
      </material>
      <material>
        <id>5</id>
        <material_name>Artifact</material_name>
      </material>
    </materials>
    <category>
      <id>1</id>
      <name>Warrior Weapons</name>
    </category>
    <equipment>
      <id>55</id>
      <equipment_name>Ursine Maulers</equipment_name>
      <category>1</category>
    </equipment>
    <recipes>
      <recipe>
        <equipment_id>55</equipment_id>
        <material_id>1</material_id>
        <material_quantity>12</material_quantity>
      </recipe>
      <recipe>
        <equipment_id>55</equipment_id>
        <material_id>2</material_id>
        <material_quantity>20</material_quantity>
      </recipe>
      <recipe>
        <equipment_id>55</equipment_id>
        <material_id>5</material_id>
        <material_quantity>1</material_quantity>
      </recipe>
    </recipes>
  </Gear>
  <Gear id="56">
    <materials>
      <material>
        <id>1</id>
        <material_name>Bar</material_name>
      </material>
      <material>
        <id>2</id>
        <material_name>Leather</material_name>
      </material>
      <material>
        <id>5</id>
        <material_name>Artifact</material_name>
      </material>
    </materials>
    <category>
      <id>1</id>
      <name>Warrior Weapons</name>
    </category>
    <equipment>
      <id>56</id>
      <equipment_name>Ravenstrike Cestus</equipment_name>
      <category>1</category>
    </equipment>
    <recipes>
      <recipe>
        <equipment_id>56</equipment_id>
        <material_id>1</material_id>
        <material_quantity>12</material_quantity>
      </recipe>
      <recipe>
        <equipment_id>56</equipment_id>
        <material_id>2</material_id>
        <material_quantity>20</material_quantity>
      </recipe>
      <recipe>
        <equipment_id>56</equipment_id>
        <material_id>5</material_id>
        <material_quantity>1</material_quantity>
      </recipe>
    </recipes>
  </Gear>
  <Gear id="57">
    <materials>
      <material>
        <id>1</id>
        <material_name>Bar</material_name>
      </material>
      <material>
        <id>2</id>
        <material_name>Leather</material_name>
      </material>
    </materials>
    <category>
      <id>1</id>
      <name>Warrior Weapons</name>
    </category>
    <equipment>
      <id>57</id>
      <equipment_name>Brawler Gloves</equipment_name>
      <category>1</category>
    </equipment>
    <recipes>
      <recipe>
        <equipment_id>57</equipment_id>
        <material_id>1</material_id>
        <material_quantity>12</material_quantity>
      </recipe>
      <recipe>
        <equipment_id>57</equipment_id>
        <material_id>2</material_id>
        <material_quantity>20</material_quantity>
      </recipe>
    </recipes>
  </Gear>
  <Gear id="58">
    <materials>
      <material>
        <id>1</id>
        <material_name>Bar</material_name>
      </material>
      <material>
        <id>2</id>
        <material_name>Leather</material_name>
      </material>
    </materials>
    <category>
      <id>1</id>
      <name>Warrior Weapons</name>
    </category>
    <equipment>
      <id>58</id>
      <equipment_name>Battle Bracers</equipment_name>
      <category>1</category>
    </equipment>
    <recipes>
      <recipe>
        <equipment_id>58</equipment_id>
        <material_id>1</material_id>
        <material_quantity>12</material_quantity>
      </recipe>
      <recipe>
        <equipment_id>58</equipment_id>
        <material_id>2</material_id>
        <material_quantity>20</material_quantity>
      </recipe>
    </recipes>
  </Gear>
  <Gear id="59">
    <materials>
      <material>
        <id>1</id>
        <material_name>Bar</material_name>
      </material>
      <material>
        <id>2</id>
        <material_name>Leather</material_name>
      </material>
    </materials>
    <category>
      <id>1</id>
      <name>Warrior Weapons</name>
    </category>
    <equipment>
      <id>59</id>
      <equipment_name>Spiked Gauntlets</equipment_name>
      <category>1</category>
    </equipment>
    <recipes>
      <recipe>
        <equipment_id>59</equipment_id>
        <material_id>1</material_id>
        <material_quantity>12</material_quantity>
      </recipe>
      <recipe>
        <equipment_id>59</equipment_id>
        <material_id>2</material_id>
        <material_quantity>20</material_quantity>
      </recipe>
    </recipes>
  </Gear>
  <Gear id="60">
    <materials>
      <material>
        <id>1</id>
        <material_name>Bar</material_name>
      </material>
      <material>
        <id>3</id>
        <material_name>Plank</material_name>
      </material>
    </materials>
    <category>
      <id>1</id>
      <name>Warrior Weapons</name>
    </category>
    <equipment>
      <id>60</id>
      <equipment_name>Crossbow</equipment_name>
      <category>1</category>
    </equipment>
    <recipes>
      <recipe>
        <equipment_id>60</equipment_id>
        <material_id>1</material_id>
        <material_quantity>12</material_quantity>
      </recipe>
      <recipe>
        <equipment_id>60</equipment_id>
        <material_id>3</material_id>
        <material_quantity>20</material_quantity>
      </recipe>
    </recipes>
  </Gear>
  <Gear id="61">
    <materials>
      <material>
        <id>1</id>
        <material_name>Bar</material_name>
      </material>
      <material>
        <id>3</id>
        <material_name>Plank</material_name>
      </material>
      <material>
        <id>5</id>
        <material_name>Artifact</material_name>
      </material>
    </materials>
    <category>
      <id>1</id>
      <name>Warrior Weapons</name>
    </category>
    <equipment>
      <id>61</id>
      <equipment_name>Energy Shaper</equipment_name>
      <category>1</category>
    </equipment>
    <recipes>
      <recipe>
        <equipment_id>61</equipment_id>
        <material_id>1</material_id>
        <material_quantity>12</material_quantity>
      </recipe>
      <recipe>
        <equipment_id>61</equipment_id>
        <material_id>3</material_id>
        <material_quantity>20</material_quantity>
      </recipe>
      <recipe>
        <equipment_id>61</equipment_id>
        <material_id>5</material_id>
        <material_quantity>1</material_quantity>
      </recipe>
    </recipes>
  </Gear>
  <Gear id="62">
    <materials>
      <material>
        <id>1</id>
        <material_name>Bar</material_name>
      </material>
      <material>
        <id>3</id>
        <material_name>Plank</material_name>
      </material>
      <material>
        <id>5</id>
        <material_name>Artifact</material_name>
      </material>
    </materials>
    <category>
      <id>1</id>
      <name>Warrior Weapons</name>
    </category>
    <equipment>
      <id>62</id>
      <equipment_name>Siege Bow</equipment_name>
      <category>1</category>
    </equipment>
    <recipes>
      <recipe>
        <equipment_id>62</equipment_id>
        <material_id>1</material_id>
        <material_quantity>12</material_quantity>
      </recipe>
      <recipe>
        <equipment_id>62</equipment_id>
        <material_id>3</material_id>
        <material_quantity>20</material_quantity>
      </recipe>
      <recipe>
        <equipment_id>62</equipment_id>
        <material_id>5</material_id>
        <material_quantity>1</material_quantity>
      </recipe>
    </recipes>
  </Gear>
  <Gear id="63">
    <materials>
      <material>
        <id>1</id>
        <material_name>Bar</material_name>
      </material>
      <material>
        <id>3</id>
        <material_name>Plank</material_name>
      </material>
    </materials>
    <category>
      <id>1</id>
      <name>Warrior Weapons</name>
    </category>
    <equipment>
      <id>63</id>
      <equipment_name>Light Crossbow</equipment_name>
      <category>1</category>
    </equipment>
    <recipes>
      <recipe>
        <equipment_id>63</equipment_id>
        <material_id>1</material_id>
        <material_quantity>8</material_quantity>
      </recipe>
      <recipe>
        <equipment_id>63</equipment_id>
        <material_id>3</material_id>
        <material_quantity>16</material_quantity>
      </recipe>
    </recipes>
  </Gear>
  <Gear id="64">
    <materials>
      <material>
        <id>1</id>
        <material_name>Bar</material_name>
      </material>
      <material>
        <id>3</id>
        <material_name>Plank</material_name>
      </material>
      <material>
        <id>5</id>
        <material_name>Artifact</material_name>
      </material>
    </materials>
    <category>
      <id>1</id>
      <name>Warrior Weapons</name>
    </category>
    <equipment>
      <id>64</id>
      <equipment_name>Weeping Repeater</equipment_name>
      <category>1</category>
    </equipment>
    <recipes>
      <recipe>
        <equipment_id>64</equipment_id>
        <material_id>1</material_id>
        <material_quantity>12</material_quantity>
      </recipe>
      <recipe>
        <equipment_id>64</equipment_id>
        <material_id>3</material_id>
        <material_quantity>20</material_quantity>
      </recipe>
      <recipe>
        <equipment_id>64</equipment_id>
        <material_id>5</material_id>
        <material_quantity>1</material_quantity>
      </recipe>
    </recipes>
  </Gear>
  <Gear id="65">
    <materials>
      <material>
        <id>1</id>
        <material_name>Bar</material_name>
      </material>
      <material>
        <id>3</id>
        <material_name>Plank</material_name>
      </material>
      <material>
        <id>5</id>
        <material_name>Artifact</material_name>
      </material>
    </materials>
    <category>
      <id>1</id>
      <name>Warrior Weapons</name>
    </category>
    <equipment>
      <id>65</id>
      <equipment_name>Boltcaster</equipment_name>
      <category>1</category>
    </equipment>
    <recipes>
      <recipe>
        <equipment_id>65</equipment_id>
        <material_id>1</material_id>
        <material_quantity>12</material_quantity>
      </recipe>
      <recipe>
        <equipment_id>65</equipment_id>
        <material_id>3</material_id>
        <material_quantity>20</material_quantity>
      </recipe>
      <recipe>
        <equipment_id>65</equipment_id>
        <material_id>5</material_id>
        <material_quantity>1</material_quantity>
      </recipe>
    </recipes>
  </Gear>
  <Gear id="66">
    <materials>
      <material>
        <id>1</id>
        <material_name>Bar</material_name>
      </material>
      <material>
        <id>3</id>
        <material_name>Plank</material_name>
      </material>
    </materials>
    <category>
      <id>4</id>
      <name>Warrior Armours</name>
    </category>
    <equipment>
      <id>66</id>
      <equipment_name>Shield</equipment_name>
      <category>4</category>
    </equipment>
    <recipes>
      <recipe>
        <equipment_id>66</equipment_id>
        <material_id>1</material_id>
        <material_quantity>4</material_quantity>
      </recipe>
      <recipe>
        <equipment_id>66</equipment_id>
        <material_id>3</material_id>
        <material_quantity>4</material_quantity>
      </recipe>
    </recipes>
  </Gear>
  <Gear id="67">
    <materials>
      <material>
        <id>1</id>
        <material_name>Bar</material_name>
      </material>
      <material>
        <id>3</id>
        <material_name>Plank</material_name>
      </material>
      <material>
        <id>5</id>
        <material_name>Artifact</material_name>
      </material>
    </materials>
    <category>
      <id>4</id>
      <name>Warrior Armours</name>
    </category>
    <equipment>
      <id>67</id>
      <equipment_name>Astral Aegis</equipment_name>
      <category>4</category>
    </equipment>
    <recipes>
      <recipe>
        <equipment_id>67</equipment_id>
        <material_id>1</material_id>
        <material_quantity>4</material_quantity>
      </recipe>
      <recipe>
        <equipment_id>67</equipment_id>
        <material_id>3</material_id>
        <material_quantity>4</material_quantity>
      </recipe>
      <recipe>
        <equipment_id>67</equipment_id>
        <material_id>5</material_id>
        <material_quantity>1</material_quantity>
      </recipe>
    </recipes>
  </Gear>
  <Gear id="68">
    <materials>
      <material>
        <id>1</id>
        <material_name>Bar</material_name>
      </material>
      <material>
        <id>3</id>
        <material_name>Plank</material_name>
      </material>
      <material>
        <id>5</id>
        <material_name>Artifact</material_name>
      </material>
    </materials>
    <category>
      <id>4</id>
      <name>Warrior Armours</name>
    </category>
    <equipment>
      <id>68</id>
      <equipment_name>Caitiff Shield</equipment_name>
      <category>4</category>
    </equipment>
    <recipes>
      <recipe>
        <equipment_id>68</equipment_id>
        <material_id>1</material_id>
        <material_quantity>4</material_quantity>
      </recipe>
      <recipe>
        <equipment_id>68</equipment_id>
        <material_id>3</material_id>
        <material_quantity>4</material_quantity>
      </recipe>
      <recipe>
        <equipment_id>68</equipment_id>
        <material_id>5</material_id>
        <material_quantity>1</material_quantity>
      </recipe>
    </recipes>
  </Gear>
  <Gear id="69">
    <materials>
      <material>
        <id>1</id>
        <material_name>Bar</material_name>
      </material>
      <material>
        <id>3</id>
        <material_name>Plank</material_name>
      </material>
      <material>
        <id>5</id>
        <material_name>Artifact</material_name>
      </material>
    </materials>
    <category>
      <id>4</id>
      <name>Warrior Armours</name>
    </category>
    <equipment>
      <id>69</id>
      <equipment_name>Sarcophagus</equipment_name>
      <category>4</category>
    </equipment>
    <recipes>
      <recipe>
        <equipment_id>69</equipment_id>
        <material_id>1</material_id>
        <material_quantity>4</material_quantity>
      </recipe>
      <recipe>
        <equipment_id>69</equipment_id>
        <material_id>3</material_id>
        <material_quantity>4</material_quantity>
      </recipe>
      <recipe>
        <equipment_id>69</equipment_id>
        <material_id>5</material_id>
        <material_quantity>1</material_quantity>
      </recipe>
    </recipes>
  </Gear>
  <Gear id="70">
    <materials>
      <material>
        <id>1</id>
        <material_name>Bar</material_name>
      </material>
      <material>
        <id>3</id>
        <material_name>Plank</material_name>
      </material>
      <material>
        <id>5</id>
        <material_name>Artifact</material_name>
      </material>
    </materials>
    <category>
      <id>4</id>
      <name>Warrior Armours</name>
    </category>
    <equipment>
      <id>70</id>
      <equipment_name>Facebreaker</equipment_name>
      <category>4</category>
    </equipment>
    <recipes>
      <recipe>
        <equipment_id>70</equipment_id>
        <material_id>1</material_id>
        <material_quantity>4</material_quantity>
      </recipe>
      <recipe>
        <equipment_id>70</equipment_id>
        <material_id>3</material_id>
        <material_quantity>4</material_quantity>
      </recipe>
      <recipe>
        <equipment_id>70</equipment_id>
        <material_id>5</material_id>
        <material_quantity>1</material_quantity>
      </recipe>
    </recipes>
  </Gear>
</root>